FSM1011Mealyoverlap.v
module FSM1011Mealyoverlap(
    input clk,
    input in,
    input rst,
    output reg out
);
reg [2:0] state;
parameter s0=0,s1=1,s2=2,s3=3;
always @(posedge clk) begin
    if(rst)begin
      out<=0;
      state<=s0;
    end
    else begin
      case (state)
        s0:begin
          out<=0;
          state<=in?s1:s0;
        end 
        s1:begin
          out<=0;
          state<=in?s1:s2;
        end 
        s2:begin
          out<=0;
          state<=in?s3:s0;
        end 
        s3:begin
          out<=in?1:0;
          state<=in?s1:s2;
        end 
        default:begin
          out<=0;
          state<=s0;
        end 
      endcase
    end
    
end
endmodule

FSM1011Mealyoverlaptb.v
`timescale 1ps/1ps
`include "FSM1011Mealyoverlap.v"
module FSM1011MealyNonoverlaptb();
reg clk,in,rst;
wire out;
FSM1011Mealyoverlap DUT(
    .clk(clk),
    .rst(rst),
    .in(in),
    .out(out)
);
initial begin
    clk=1'b0;
    rst=1'b1;
    #15 rst=1'b0;
end
initial forever begin
    #5 clk=~clk;   
end
initial begin
    $monitor("%t,rst=%b,in=%b,state=%b,out=%b",$time,rst,in,DUT.state,out);
    $dumpfile("FSM1011Mealyoverlap.vcd");
    $dumpvars;
end
initial begin
    #15 in=1'b0;
    #10 in=1'b0;
    #10 in=1'b1;
    #10 in=1'b0;
    #10 in=1'b1;
    #10 in=1'b1;
    #10 in=1'b0;
    #10 in=1'b1;
    #10 in=1'b1;
    #10 in=1'b1;
    #10 in=1'b1;
    #10 in=1'b0;
    #10 in=1'b1;
    #10 in=1'b1;
    #10 in=1'b0;
    #20 $finish;
end

endmodule

FSM1011Mealyoverlap.vcd
$date
	Sun Aug 13 19:15:44 2023
$end
$version
	Icarus Verilog
$end
$timescale
	1ps
$end
$scope module FSM1011MealyNonoverlaptb $end
$var wire 1 ! out $end
$var reg 1 " clk $end
$var reg 1 # in $end
$var reg 1 $ rst $end
$scope module DUT $end
$var wire 1 " clk $end
$var wire 1 # in $end
$var wire 1 $ rst $end
$var parameter 32 % s0 $end
$var parameter 32 & s1 $end
$var parameter 32 ' s2 $end
$var parameter 32 ( s3 $end
$var reg 1 ! out $end
$var reg 3 ) state [2:0] $end
$upscope $end
$upscope $end
$enddefinitions $end
$comment Show the parameter values. $end
$dumpall
b11 (
b10 '
b1 &
b0 %
$end
#0
$dumpvars
bx )
1$
x#
0"
x!
$end
#5
b0 )
0!
1"
#10
0"
#15
1"
0#
0$
#20
0"
#25
1"
#30
0"
#35
b1 )
1"
1#
#40
0"
#45
b10 )
1"
0#
#50
0"
#55
b11 )
1"
1#
#60
0"
#65
b1 )
1!
1"
#70
0"
#75
b10 )
0!
1"
0#
#80
0"
#85
b11 )
1"
1#
#90
0"
#95
b1 )
1!
1"
#100
0"
#105
0!
1"
#110
0"
#115
1"
#120
0"
#125
b10 )
1"
0#
#130
0"
#135
b11 )
1"
1#
#140
0"
#145
b1 )
1!
1"
#150
0"
#155
b10 )
0!
1"
0#
#160
0"
#165
b0 )
1"
