FSM101Moore.v

module FSM101Moore (
    input clk,
    input rst,
    input in,
    output reg out
);
reg [2:0] PS,NS;
parameter s0=0,s1=1,s2=2,s3=3;
always @(posedge clk) begin
    if(rst) begin
      out<=0;
      PS<=s0;
    end
    else PS<=NS;
end
always @(PS,in) begin
    case(PS)
        s0: begin
          out=0;
          NS=in?s1:s0;
        end
        s1: begin
          out=0;
          NS=in?s1:s2;
        end
        s2: begin
          out=0;
          NS=in?s3:s0;
        end
        s3: begin
          out=1;
          NS=in?s1:s2;
        end
       
    endcase
end
    
endmodule

FSM101Mooretb.v
`timescale 1ps/1ps
`include "FSM101Moore.v"
module FSM101Mooretb();
reg in,rst,clk;
wire out;
FSM101Moore DUT(
    .clk(clk),
    .rst(rst),
    .in(in),
    .out(out)
);
initial begin
    clk=1'b0;
    rst=1'b1;
    #15 rst=1'b0;
end
initial forever begin
    #5 clk=!clk;
end
initial begin
    $monitor("%t,in=%b,PS=%b,out=%b",$time,in,DUT.PS,out);
    $dumpfile("FSM101Moore.vcd");
    $dumpvars;
end
initial begin
    #15 in=1'b0;
    #10 in=1'b0;
    #10 in=1'b1;
    #10 in=1'b0;
    #10 in=1'b1;
    #10 in=1'b0;
    #10 in=1'b1;
    #10 in=1'b0;
    #20 $finish;
end
endmodule

FSM101Moore.vcd
$date
	Sun Aug 13 16:38:50 2023
$end
$version
	Icarus Verilog
$end
$timescale
	1ps
$end
$scope module FSM101Mooretb $end
$var wire 1 ! out $end
$var reg 1 " clk $end
$var reg 1 # in $end
$var reg 1 $ rst $end
$scope module DUT $end
$var wire 1 " clk $end
$var wire 1 # in $end
$var wire 1 $ rst $end
$var parameter 32 % s0 $end
$var parameter 32 & s1 $end
$var parameter 32 ' s2 $end
$var parameter 32 ( s3 $end
$var reg 3 ) NS [2:0] $end
$var reg 3 * PS [2:0] $end
$var reg 1 ! out $end
$upscope $end
$upscope $end
$enddefinitions $end
$comment Show the parameter values. $end
$dumpall
b11 (
b10 '
b1 &
b0 %
$end
#0
$dumpvars
bx *
bx )
1$
x#
0"
x!
$end
#5
b0x )
b0 *
0!
1"
#10
0"
#15
b0 )
1"
0#
0$
#20
0"
#25
1"
#30
0"
#35
b1 *
b1 )
1"
1#
#40
0"
#45
b10 *
b0 )
1"
0#
#50
0"
#55
1!
b11 *
b1 )
1"
1#
#60
0"
#65
0!
b10 *
b0 )
1"
0#
#70
0"
#75
1!
b11 *
b1 )
1"
1#
#80
0"
#85
0!
b10 *
b0 )
1"
0#
#90
0"
#95
b0 *
1"
