FSM_1101_MealyMachine.v
`timescale 1ps/1ps
module FSM1101(
    input clk,
    input rst,
    input in,
    output reg out
);
parameter S0 =0,
          S1=1,
          S2=2,
          S3=3 ;
reg [1:0] state;
always @(posedge clk) begin
    if(rst)
        begin
            out<=0;
            state<=0;
        end
    else
        begin
            case(state)
            S0:begin
                state<=in?S1:S0;
                out<=0;
               end
            S1:begin
                state<=in?S2:S0;
                out<=0;
                end
            S2:begin
                state<=in?S2:S3;
                out<=0;
               end
            S3:begin
                state<=S0;
                out<=in?1:0;
               end
            default:begin
                    state<=S0;
                    out<=0;
                   end
            endcase
        end
end




endmodule

FSM_1101_tb.v
`timescale 1ps/1ps
`include "FSM_1101_MealyMachine.v"
module FSM_1101_tb();
reg clk,rst,in;
wire out;
FSM1101 DUT(
    .clk(clk),
    .in(in),
    .rst(rst),
    .out(out)
);
initial  begin
  clk=1'b0;
  rst=1'b1;
  #15 rst=1'b0;


end

initial forever begin
    #5 clk=~clk;
end
initial begin
  $monitor("%t||rst=%b||in=%b||out=%b||state=%d",$time,rst,in,out,DUT.state);
  $dumpfile("FSM_1101.vcd");
  $dumpvars;
end
initial begin
  #15 in=0;
  #10 in=1;#10 in=1;#10 in=0;#10 in=1;#10 in=1; #10 in=1;
  #20 $finish;
end
endmodule

FSM_1101.vcd
$date
	Sun Aug 13 00:40:22 2023
$end
$version
	Icarus Verilog
$end
$timescale
	1ps
$end
$scope module FSM_1101_tb $end
$var wire 1 ! out $end
$var reg 1 " clk $end
$var reg 1 # in $end
$var reg 1 $ rst $end
$scope module DUT $end
$var wire 1 " clk $end
$var wire 1 # in $end
$var wire 1 $ rst $end
$var parameter 32 % S0 $end
$var parameter 32 & S1 $end
$var parameter 32 ' S2 $end
$var parameter 32 ( S3 $end
$var reg 1 ! out $end
$var reg 2 ) state [1:0] $end
$upscope $end
$upscope $end
$enddefinitions $end
$comment Show the parameter values. $end
$dumpall
b11 (
b10 '
b1 &
b0 %
$end
#0
$dumpvars
bx )
1$
x#
0"
x!
$end
#5
b0 )
0!
1"
#10
0"
#15
1"
0#
0$
#20
0"
#25
b1 )
1"
1#
#30
0"
#35
b10 )
1"
#40
0"
#45
b11 )
1"
0#
#50
0"
#55
1!
b0 )
1"
1#
#60
0"
#65
0!
b1 )
1"
#70
0"
#75
b10 )
1"
